OpencvAnzhuoBianchengShiliChuyiFix1/README.md
OpencvAnzhuoBianchengShiliChuyiFix1/__init__.py
OpencvAnzhuoBianchengShiliChuyiFix1/__main__.py
OpencvAnzhuoBianchengShiliChuyiFix1/file.epub
OpencvAnzhuoBianchengShiliChuyiFix1/index.html
OpencvAnzhuoBianchengShiliChuyiFix1/css/__init__.py
OpencvAnzhuoBianchengShiliChuyiFix1/css/annotations.css
OpencvAnzhuoBianchengShiliChuyiFix1/css/main.css
OpencvAnzhuoBianchengShiliChuyiFix1/css/normalize.css
OpencvAnzhuoBianchengShiliChuyiFix1/css/popup.css
OpencvAnzhuoBianchengShiliChuyiFix1/font/__init__.py
OpencvAnzhuoBianchengShiliChuyiFix1/font/fontello.eot
OpencvAnzhuoBianchengShiliChuyiFix1/font/fontello.svg
OpencvAnzhuoBianchengShiliChuyiFix1/font/fontello.ttf
OpencvAnzhuoBianchengShiliChuyiFix1/font/fontello.woff
OpencvAnzhuoBianchengShiliChuyiFix1/img/__init__.py
OpencvAnzhuoBianchengShiliChuyiFix1/img/annotator-glyph-sprite.png
OpencvAnzhuoBianchengShiliChuyiFix1/img/annotator-icon-sprite.png
OpencvAnzhuoBianchengShiliChuyiFix1/img/apple-touch-icon.png
OpencvAnzhuoBianchengShiliChuyiFix1/img/cancelfullscreen.png
OpencvAnzhuoBianchengShiliChuyiFix1/img/close.png
OpencvAnzhuoBianchengShiliChuyiFix1/img/fullscreen.png
OpencvAnzhuoBianchengShiliChuyiFix1/img/loader.gif
OpencvAnzhuoBianchengShiliChuyiFix1/img/menu-icon.png
OpencvAnzhuoBianchengShiliChuyiFix1/img/save.png
OpencvAnzhuoBianchengShiliChuyiFix1/img/saved.png
OpencvAnzhuoBianchengShiliChuyiFix1/img/settings-s.png
OpencvAnzhuoBianchengShiliChuyiFix1/img/settings.png
OpencvAnzhuoBianchengShiliChuyiFix1/img/star.png
OpencvAnzhuoBianchengShiliChuyiFix1/js/__init__.py
OpencvAnzhuoBianchengShiliChuyiFix1/js/epub.js
OpencvAnzhuoBianchengShiliChuyiFix1/js/epub.min.js
OpencvAnzhuoBianchengShiliChuyiFix1/js/epub.min.map
OpencvAnzhuoBianchengShiliChuyiFix1/js/hooks.min.js
OpencvAnzhuoBianchengShiliChuyiFix1/js/hooks.min.map
OpencvAnzhuoBianchengShiliChuyiFix1/js/reader.js
OpencvAnzhuoBianchengShiliChuyiFix1/js/reader.js.map
OpencvAnzhuoBianchengShiliChuyiFix1/js/reader.min.js
opencv_anzhuo_biancheng_shili_chuyi_fix1-2025.3.25.1.dist-info/METADATA
opencv_anzhuo_biancheng_shili_chuyi_fix1-2025.3.25.1.dist-info/WHEEL
opencv_anzhuo_biancheng_shili_chuyi_fix1-2025.3.25.1.dist-info/entry_points.txt
opencv_anzhuo_biancheng_shili_chuyi_fix1-2025.3.25.1.dist-info/top_level.txt
opencv_anzhuo_biancheng_shili_chuyi_fix1-2025.3.25.1.dist-info/RECORD
